Metadata-Version: 1.1
Name: argcompd
Version: 0.9.0.0
Summary: A package providing automated shell completion support for argparse.
Home-page: https://github.com/d-e-s-o/argcomp
Author: Daniel Mueller
Author-email: deso@posteo.net
License: GPLv3
Keywords: argcomp argparse ArgumentParser shell completion
Platform: UNKNOWN
Classifier: Development Status :: 3 - Alpha
Classifier: Environment :: Console
Classifier: Intended Audience :: Developers
Classifier: License :: OSI Approved :: GNU General Public License v3 (GPLv3)
Classifier: Operating System :: OS Independent
Classifier: Programming Language :: Python
Classifier: Programming Language :: Python :: 3
Classifier: Topic :: Software Development :: User Interfaces
Classifier: Topic :: Software Development :: Libraries :: Python Modules
Classifier: Topic :: System :: Shells
